LICENSE.txt
MANIFEST.in
README.rst
setup.py
tw2/__init__.py
tw2.d3.egg-info/PKG-INFO
tw2.d3.egg-info/SOURCES.txt
tw2.d3.egg-info/dependency_links.txt
tw2.d3.egg-info/entry_points.txt
tw2.d3.egg-info/namespace_packages.txt
tw2.d3.egg-info/not-zip-safe
tw2.d3.egg-info/requires.txt
tw2.d3.egg-info/top_level.txt
tw2/d3/__init__.py
tw2/d3/samples.py
tw2/d3/widgets.py
tw2/d3/static/ext/bar.css
tw2/d3/static/ext/bar.js
tw2/d3/static/ext/timeseries.css
tw2/d3/static/ext/timeseries.js
tw2/d3/static/js/2.8.0/d3.v2.js
tw2/d3/static/js/2.8.0/d3.v2.min.js
tw2/d3/templates/__init__.py
tw2/d3/templates/__init__.pyc
tw2/d3/templates/d3.mak