Metadata-Version: 1.1
Name: tw2.d3
Version: 0.0.8
Summary: toscawidgets2 wrapper for d3 (data-driven documents)
Home-page: http://github.com/toscawidgets/tw2.d3
Author: Ralph Bean
Author-email: rbean@redhat.com
License: UNKNOWN
Keywords: toscawidgets.widgets
Platform: UNKNOWN
Classifier: Development Status :: 4 - Beta
Classifier: Environment :: Web Environment
Classifier: Environment :: Web Environment :: ToscaWidgets
Classifier: Topic :: Software Development :: Libraries :: Python Modules
Classifier: Topic :: Software Development :: Widget Sets
Classifier: Intended Audience :: Developers
Classifier: Operating System :: OS Independent
Classifier: Programming Language :: Python
Classifier: Programming Language :: JavaScript
